generate/__init__.py
generate/generate_code.py
generate/templates/controller.tpl
generate/templates/service.tpl
generate/templates/sql.tpl
hj_generate-3.1.0.dist-info/METADATA
hj_generate-3.1.0.dist-info/WHEEL
hj_generate-3.1.0.dist-info/entry_points.txt
hj_generate-3.1.0.dist-info/top_level.txt
hj_generate-3.1.0.dist-info/RECORD
