Metadata-Version: 2.1
Name: hj-generate
Version: 3.1.0
Summary: 代码生成
Author: hj
Author-email: 864655329@qq.com
Requires-Dist: Jinja2
